{
	"main.js": "js/main.e4d90c8ea136679339ac.js",
	"assets/add-eLjfck.svg": "assets/add-eLjfck.svg",
	"assets/arrow-down-1-dzphtd.svg": "assets/arrow-down-1-dzphtd.svg",
	"assets/arrow-left-1-dzpa9L.svg": "assets/arrow-left-1-dzpa9L.svg",
	"assets/arrow-left-1-itskPx.svg": "assets/arrow-left-1-itskPx.svg",
	"assets/arrow-left-dzpnnb.svg": "assets/arrow-left-dzpnnb.svg",
	"assets/arrow-right-1-Ei8Dl0.svg": "assets/arrow-right-1-Ei8Dl0.svg",
	"assets/arrow-right-1-Nc3Zm6.svg": "assets/arrow-right-1-Nc3Zm6.svg",
	"assets/arrow-right-Nc34uf.svg": "assets/arrow-right-Nc34uf.svg",
	"assets/close-232XyC.svg": "assets/close-232XyC.svg",
	"assets/common-file-question-ZOslf3.svg": "assets/common-file-question-ZOslf3.svg",
	"assets/common-file-text-jHWHye.svg": "assets/common-file-text-jHWHye.svg",
	"assets/controls-play-af7Jis.svg": "assets/controls-play-af7Jis.svg",
	"assets/download-bottom-M5p7BQ.svg": "assets/download-bottom-M5p7BQ.svg",
	"assets/loading-half-7QUSw4.svg": "assets/loading-half-7QUSw4.svg",
	"assets/loading-half-7QUSw4.svg.gz": "assets/loading-half-7QUSw4.svg.gz",
	"assets/lock-1-g0YpCK.svg": "assets/lock-1-g0YpCK.svg",
	"assets/login-P2Woe5.svg": "assets/login-P2Woe5.svg",
	"assets/love-it-08UZOs.svg": "assets/love-it-08UZOs.svg",
	"assets/move-down-1-fSZQ4o.svg": "assets/move-down-1-fSZQ4o.svg",
	"assets/move-left-1-fSZYq5.svg": "assets/move-left-1-fSZYq5.svg",
	"assets/move-right-1-fSZYYL.svg": "assets/move-right-1-fSZYYL.svg",
	"assets/move-up-1-hNEO9b.svg": "assets/move-up-1-hNEO9b.svg",
	"assets/navigation-menu-gWaHY4.svg": "assets/navigation-menu-gWaHY4.svg",
	"assets/rating-star-J4vaWN.svg": "assets/rating-star-J4vaWN.svg",
	"assets/rating-star-gWaXzP.svg": "assets/rating-star-gWaXzP.svg",
	"assets/search-jUAwYE.svg": "assets/search-jUAwYE.svg",
	"assets/shipment-upload-PvJIK9.svg": "assets/shipment-upload-PvJIK9.svg",
	"assets/shopping-bag-tag-1-7QUX0n.svg": "assets/shopping-bag-tag-1-7QUX0n.svg",
	"assets/shrink-horizontal-y7qSce.svg": "assets/shrink-horizontal-y7qSce.svg",
	"assets/shrink-vertical-y7qZWz.svg": "assets/shrink-vertical-y7qZWz.svg",
	"assets/single-neutral-3ziDl0.svg": "assets/single-neutral-3ziDl0.svg",
	"assets/subtract-gWaFt8.svg": "assets/subtract-gWaFt8.svg",
	"js/main.e4d90c8ea136679339ac.js.gz": "js/main.e4d90c8ea136679339ac.js.gz",
	"assets/arrow-down-1-sjsMh6.svg": "assets/arrow-down-1-sjsMh6.svg",
	"assets/klarna.svg": "assets/klarna.svg",
	"assets/search-1-jUAiDQ.svg": "assets/search-1-jUAiDQ.svg"
}